dfeqa/__about__.py
dfeqa/__init__.py
dfeqa/__main__.py
dfeqa/cmdline.py
dfeqa/data_transformation.py
dfeqa/data_validation.py
dfeqa/datastructures.py
dfeqa/db.py
dfeqa/exceptions.py
dfeqa/summaries.py
dfeqa/template.env
dfeqa/commands/__init__.py
dfeqa/commands/addenv.py
dfeqa/commands/create.py
dfeqa/commands/version.py
dfeqa/templates/census_dq.html
dfeqa/templates/census_dq.qmd
dfeqa/templates/data_quality.html
dfeqa/templates/data_quality.qmd
dfeqa/templates/qa_report.html
dfeqa/templates/qa_report.qmd
dfeqa-0.0.6.dist-info/METADATA
dfeqa-0.0.6.dist-info/WHEEL
dfeqa-0.0.6.dist-info/entry_points.txt
dfeqa-0.0.6.dist-info/licenses/LICENSE
dfeqa-0.0.6.dist-info/RECORD
