Metadata-Version: 2.4
Name: dfeqa
Version: 0.0.6
Summary: helpers for quality checking data
Project-URL: Documentation, https://github.com/quhack/dfeqa/wiki
Project-URL: Repository, https://github.com/quhack/dfeqa
Project-URL: Issues, https://github.com/quhack/dfeqa/issues
Author-email: mrheducation <martin1.harris@education.gov.uk>
License-File: LICENSE
Classifier: License :: OSI Approved :: MIT License
Classifier: Operating System :: OS Independent
Classifier: Programming Language :: Python :: 3
Requires-Python: >=3.8
Requires-Dist: jinja2
Requires-Dist: pandas
Requires-Dist: python-dotenv
Requires-Dist: regex
Requires-Dist: seaborn
Requires-Dist: sqlalchemy
Provides-Extra: databricks
Requires-Dist: databricks-sql-connector; extra == 'databricks'
Requires-Dist: databricks-sqlalchemy; extra == 'databricks'
Requires-Dist: ipykernel; extra == 'databricks'
Requires-Dist: nbclient; extra == 'databricks'
Requires-Dist: nbformat; extra == 'databricks'
Requires-Dist: pyyaml; extra == 'databricks'
Requires-Dist: quarto; extra == 'databricks'
Provides-Extra: odbc
Requires-Dist: ipykernel; extra == 'odbc'
Requires-Dist: nbclient; extra == 'odbc'
Requires-Dist: nbformat; extra == 'odbc'
Requires-Dist: pyodbc; extra == 'odbc'
Requires-Dist: pyyaml; extra == 'odbc'
Requires-Dist: quarto; extra == 'odbc'
Provides-Extra: user
Requires-Dist: ipykernel; extra == 'user'
Requires-Dist: nbclient; extra == 'user'
Requires-Dist: nbformat; extra == 'user'
Requires-Dist: pyyaml; extra == 'user'
Requires-Dist: quarto; extra == 'user'
